Workbook

Sheet Raw_Data
A1: Order_ID | B1: Date | C1: Region | D1: City | E1: Category | F1: Product | G1: Customer_Type | H1: Sales | I1: Quantity | J1: Discount | K1: Profit
A2: 1001 | B2: 45009 | C2: West | D2: Mumbai | E2: Electronics | F2: Mobile | G2: Consumer | H2: 22000 | I2: 1 | J2: 0.08 | K2: 3200
A3: 1002 | B3: 44998 | C3: North | D3: Delhi | E3: Furniture | F3: Chair | G3: Corporate | H3: 7000 | I3: 1 | J3: 0.15 | K3: 1200
A4: 1003 | B4: 44969 | C4: South | D4: Bangalore | E4: Clothing | F4: T-Shirt | G4: Consumer | H4: 1500 | I4: 3 | J4: 0.05 | K4: 400
A5: 1004 | B5: 44970 | C5: East | D5: Kolkata | E5: Electronics | F5: Laptop | G5: Home Office | H5: 55000 | I5: 1 | J5: 0.06 | K5: 7000
A6: 1005 | B6: 44986 | C6: West | D6: Pune | E6: Furniture | F6: Table | G6: Consumer | H6: 9000 | I6: 1 | J6: 0.12 | K6: 1500
A7: 1006 | B7: 44960 | C7: North | D7: Jaipur | E7: Clothing | F7: Jeans | G7: Corporate | H7: 2500 | I7: 2 | J7: 0.1 | K7: 600
A8: 1007 | B8: 44929 | C8: South | D8: Chennai | E8: Electronics | F8: Tablet | G8: Consumer | H8: 15000 | I8: 1 | J8: 0.07 | K8: 2200
A9: 1008 | B9: 44946 | C9: East | D9: Patna | E9: Furniture | F9: Sofa | G9: Home Office | H9: 30000 | I9: 1 | J9: 0.18 | K9: 4000
A10: 1009 | B10: 44958 | C10: West | D10: Mumbai | E10: Clothing | F10: Jacket | G10: Consumer | H10: 3500 | I10: 1 | J10: 0.1 | K10: 800
A11: 1010 | B11: 44984 | C11: North | D11: Delhi | E11: Electronics | F11: Headphones | G11: Corporate | H11: 3000 | I11: 2 | J11: 0.08 | K11: 600
A12: 1011 | B12: 44948 | C12: South | D12: Bangalore | E12: Furniture | F12: Chair | G12: Consumer | H12: 6000 | I12: 1 | J12: 0.1 | K12: 1000
A13: 1012 | B13: 44934 | C13: East | D13: Kolkata | E13: Clothing | F13: Shirt | G13: Home Office | H13: 1200 | I13: 2 | J13: 0.05 | K13: 300
... A201: 1200 | B201: 44987 | C201: West | D201: Mumbai | E201: Furniture | F201: Almirah | G201: Consumer | H201: 61105 | I201: 1 | J201: 0.07 | K201: 6861

Sheet Clean_Data
A1: Order_ID | B1: Date | C1: Region | D1: City | E1: Category | F1: Product | G1: Customer_Type | H1: Sales | I1: Quantity | J1: Discount | K1: Profit | L1: Profit_Margin | M1: Status
A2: {=IF(Raw_Data!A2:A201="",, Raw_Data!A2:G201)} -> 1001 | B2: 45009 | C2: West | D2: Mumbai | E2: Electronics | F2: Mobile | G2: Consumer | H2: {=IF(Raw_Data!A2:A201="",, Raw_Data!H2:K201)} -> 22000 | I2: 1 | J2: 0.08 | K2: 3200 | L2: =IFERROR(K2/H2, 0) -> 0.14545455 | M2: =IF(AND(H2>0, K2>0, ISNUMBER(B2)), "VALID", "INVALID") -> VALID
A3: 1002 | B3: 44998 | C3: North | D3: Delhi | E3: Furniture | F3: Chair | G3: Corporate | H3: 7000 | I3: 1 | J3: 0.15 | K3: 1200 | L3: =IFERROR(K3/H3, 0) -> 0.17142857 | M3: =IF(AND(H3>0, K3>0, ISNUMBER(B3)), "VALID", "INVALID") -> VALID
A4: 1003 | B4: 44969 | C4: South | D4: Bangalore | E4: Clothing | F4: T-Shirt | G4: Consumer | H4: 1500 | I4: 3 | J4: 0.05 | K4: 400 | L4: =IFERROR(K4/H4, 0) -> 0.26666667 | M4: =IF(AND(H4>0, K4>0, ISNUMBER(B4)), "VALID", "INVALID") -> VALID
A5: 1004 | B5: 44970 | C5: East | D5: Kolkata | E5: Electronics | F5: Laptop | G5: Home Office | H5: 55000 | I5: 1 | J5: 0.06 | K5: 7000 | L5: =IFERROR(K5/H5, 0) -> 0.12727273 | M5: =IF(AND(H5>0, K5>0, ISNUMBER(B5)), "VALID", "INVALID") -> VALID
A6: 1005 | B6: 44986 | C6: West | D6: Pune | E6: Furniture | F6: Table | G6: Consumer | H6: 9000 | I6: 1 | J6: 0.12 | K6: 1500 | L6: =IFERROR(K6/H6, 0) -> 0.16666667 | M6: =IF(AND(H6>0, K6>0, ISNUMBER(B6)), "VALID", "INVALID") -> VALID
A7: 1006 | B7: 44960 | C7: North | D7: Jaipur | E7: Clothing | F7: Jeans | G7: Corporate | H7: 2500 | I7: 2 | J7: 0.1 | K7: 600 | L7: =IFERROR(K7/H7, 0) -> 0.24 | M7: =IF(AND(H7>0, K7>0, ISNUMBER(B7)), "VALID", "INVALID") -> VALID
A8: 1007 | B8: 44929 | C8: South | D8: Chennai | E8: Electronics | F8: Tablet | G8: Consumer | H8: 15000 | I8: 1 | J8: 0.07 | K8: 2200 | L8: =IFERROR(K8/H8, 0) -> 0.14666667 | M8: =IF(AND(H8>0, K8>0, ISNUMBER(B8)), "VALID", "INVALID") -> VALID
A9: 1008 | B9: 44946 | C9: East | D9: Patna | E9: Furniture | F9: Sofa | G9: Home Office | H9: 30000 | I9: 1 | J9: 0.18 | K9: 4000 | L9: =IFERROR(K9/H9, 0) -> 0.13333333 | M9: =IF(AND(H9>0, K9>0, ISNUMBER(B9)), "VALID", "INVALID") -> VALID
A10: 1009 | B10: 44958 | C10: West | D10: Mumbai | E10: Clothing | F10: Jacket | G10: Consumer | H10: 3500 | I10: 1 | J10: 0.1 | K10: 800 | L10: =IFERROR(K10/H10, 0) -> 0.22857143 | M10: =IF(AND(H10>0, K10>0, ISNUMBER(B10)), "VALID", "INVALID") -> VALID
A11: 1010 | B11: 44984 | C11: North | D11: Delhi | E11: Electronics | F11: Headphones | G11: Corporate | H11: 3000 | I11: 2 | J11: 0.08 | K11: 600 | L11: =IFERROR(K11/H11, 0) -> 0.2 | M11: =IF(AND(H11>0, K11>0, ISNUMBER(B11)), "VALID", "INVALID") -> VALID
A12: 1011 | B12: 44948 | C12: South | D12: Bangalore | E12: Furniture | F12: Chair | G12: Consumer | H12: 6000 | I12: 1 | J12: 0.1 | K12: 1000 | L12: =IFERROR(K12/H12, 0) -> 0.16666667 | M12: =IF(AND(H12>0, K12>0, ISNUMBER(B12)), "VALID", "INVALID") -> VALID
A13: 1012 | B13: 44934 | C13: East | D13: Kolkata | E13: Clothing | F13: Shirt | G13: Home Office | H13: 1200 | I13: 2 | J13: 0.05 | K13: 300 | L13: =IFERROR(K13/H13, 0) -> 0.25 | M13: =IF(AND(H13>0, K13>0, ISNUMBER(B13)), "VALID", "INVALID") -> VALID
A14: 1013 | B14: 44992 | C14: West | D14: Pune | E14: Electronics | F14: Mobile | G14: Consumer | H14: 21000 | I14: 1 | J14: 0.09 | K14: 3100 | L14: =IFERROR(K14/H14, 0) -> 0.14761905 | M14: =IF(AND(H14>0, K14>0, ISNUMBER(B14)), "VALID", "INVALID") -> VALID
... A201: 1200 | B201: 44987 | C201: West | D201: Mumbai | E201: Furniture | F201: Almirah | G201: Consumer | H201: 61105 | I201: 1 | J201: 0.07 | K201: 6861 | L201: =IFERROR(K201/H201, 0) -> 0.11228214 | M201: =IF(AND(H201>0, K201>0, ISNUMBER(B201)), "VALID", "INVALID") -> VALID

Sheet Analysis
B4: Monthly Revenue Performance | F4: Regional Sales Contribution | J4: Profit Margin By Product Category

Sheet Charts
A1: Q1 SALES PERFORMANCE DASHBOARD
D5: TOTAL REVENUE ($) | H5: MoM | L5: TOP REGION | P5: BEST CATEGORY
D6: =sum(Analysis!C6:C8) -> 2831548 | H6: =IF((Analysis!C8-Analysis!C7)/Analysis!C7>0, "▲ "&TEXT((Analysis!C8-Analysis!C7)/Analysis!C7,"0.0%"), "▼ "&TEXT(ABS((Analysis!C8-Analysis!C7)/Analysis!C7),"0.0%")) -> ▲ 14.2% | L6: {=INDEX( Analysis!F6:F9, MATCH(MAX( Analysis!G6:G9), Analysis!G6:G9, 0))} -> East | P6: {=INDEX(Analysis!J6:J8, MATCH(MAX(Analysis!K6:K8),Analysis!K6:K8, 0))} -> Electronics
B27: Analyst Note: Performance: Total Q1 revenue reached ₹2,831,548.00, peaking in January at ₹1,063,744.00, followed by a notable 14.2% recovery in March. Key Takeaway: The significant rebound in March suggests that the February dip was a temporary seasonal fluctuation rather than a shift in long-term demand. Action: Analyze inventory and marketing spend from February to identify if stockouts or reduced outreach contributed to the mid-quarter dip. | H27: Analyst Note: Performance: The East region is the primary driver of revenue, contributing ₹879,610.00, while the North region currently lags at ₹554,293.00. Key Takeaway: There is a ~37% performance gap between the East and North regions, indicating significant untapped potential in the Northern market. Action: Reallocate a portion of the Q2 marketing budget to the North region to improve brand penetration and bridge the regional sales gap. | N27: Analyst Note: Performance: Electronics leads all categories with a high average profit margin of 26.35%, whereas Clothing currently sits at the lowest point of 18.00%. Key Takeaway: While the business maintains a healthy overall average margin of 21.58%, the lower margin in Clothing is slightly suppressing total profitability. Action: Review supplier contracts for Clothing and consider implementing "bundle" deals to increase the average order value and margin for that category.
